{
    "id": "LEVEL_3",
    "blueprint": "TX_LEVEL3_BLUEPRINT",
    "backgroundMusic": "MUSIC_LEVEL_BG_C",
    "description": "TX_LEVEL_3",
    "wallColor": "Colors::PARAKEET",
    "dimensions": {
        "levelWidth": 76,
        "levelHeight": 33,
        "tileWidth": 32,
        "tileHeight": 32
    },
    "tiledLayers": [
        {
            "layer": "GameLayer::BACKGROUND_1",
            "tiledObjectId": "BACKGROUND_GRID_1",
            "tileSize": {
                "width": 512,
                "height": 512
            }
        }
    ],
    "statusItems": [
        {
            "id": "StatusItemId::PLAYERS_HEART_COUNT",
            "initialValue": 6,
            "minValue": 0,
            "maxValue": 6
        },
        {
            "id": "StatusItemId::PLAYER_WEAPON_LEVEL",
            "initialValue": 1,
            "minValue": 0,
            "maxValue": 3
        },
        {
            "id": "StatusItemId::PLAYER_WEAPON_ACCRUAL",
            "initialValue": 0,
            "minValue": 0,
            "maxValue": 50
        },
        {
            "id": "StatusItemId::PLAYER_WEAPON_CHARGED_PERCENT",
            "initialValue": 0,
            "minValue": 0,
            "maxValue": 100
        },
        {
            "id": "StatusItemId::PLAYER_WEAPON_IS_CHARGED",
            "initialValue": 0,
            "minValue": 0,
            "maxValue": 1
        },
        {
            "id": "StatusItemId::SURVIVORS",
            "initialValue": 10,
            "minValue": 0,
            "maxValue": 10
        },
        {
            "id": "StatusItemId::SCRAP_COUNT",
            "initialValue": 0,
            "minValue": 0,
            "maxValue": 2000
        }


    ],
    "objectives": [
        {
            "id": "StatusItemId::SURVIVORS",
            "targetValue": 0
        }

    ],
    "levelTriggers": [
        {
            "description": "Player Death",
            "triggerClass": "PlayerDeath"
        },
        {
            "description": "Level Complete",
            "triggerClass": "LevelComplete"
        },
        {
            "description": "Boss Dead",
            "triggerClass": "EnemyCDeadTrigger"
        }

    ],
    "colorDefinedObjects": [
        {
            "colorKey": "Colors::BLUE",
            "gameObjectType": "NAVIGATION_WAYPOINT",
            "layer": "GameLayer::ABSTRACT"
        },
        {
            "colorKey": "Colors::PURPLE",
            "gameObjectType": "VOID_FILLER",
            "layer": "GameLayer::BACKGROUND_1",
            "objectColor": "Colors::CYAN"
        },
        {
            "colorKey": "Colors::GRAPE",
            "gameObjectType": "BARREL_FILLER",
            "layer": "GameLayer::MAIN",
            "objectColor": "Colors::CYAN"
        },
        {
            "colorKey": "Colors::YELLOW",
            "gameObjectType": "SURVIVOR",
            "layer": "GameLayer::MAIN"
        }

    ],
    "locationDefinedObjects": [
        {
            "id": "LOC_0006_0004",
            "gameObjectType": "GINA_64",
            "name": "PlayerGina",
            "cameraFollow": true
        },
        {
            "id": "LOC_0003_0008",
            "gameObjectType": "HEALTH_STATION"
        },
        {
            "id": "LOC_0006_0029",
            "gameObjectType": "HEALTH_STATION"
        },
        {
            "id": "LOC_0049_0029",
            "gameObjectType": "HEALTH_STATION_96"
        },
        {
            "id": "LOC_0035_0017",
            "gameObjectType": "TURRET",
            "angle": 270,
            "brainSensorSize": 40,
            "objectColor": "Colors::RED",
            "name": "EnemyA"
        },
        {
            "id": "LOC_0019_0025",
            "gameObjectType": "DRONE2"
        },
        {
            "id": "LOC_0048_0002",
            "gameObjectType": "DRONE",
            "name": "EnemyC"
        },
        {
            "id": "LOC_0028_0019",
            "gameObjectType": "RADIATION_EMITTER",
            "angle": 0
        },
        {
            "id": "LOC_0005_0020",
            "gameObjectType": "RADIATION_EMITTER",
            "angle": 0
        },
        {
            "id": "LOC_0035_0023",
            "gameObjectType": "ONETIME_BUTTON",
            "angle": 270,
            "name": "button1"
        },
        {
            "id": "LOC_0008_0021",
            "gameObjectType": "TOGGLE_BUTTON",
            "angle": 90,
            "name": "button2"
        },
        {
            "id": "LOC_0003_0026",
            "gameObjectType": "TOGGLE_BUTTON",
            "angle": 90,
            "name": "button3"
        },
        {
            "id": "LOC_0019_0016",
            "gameObjectType": "TOGGLE_BUTTON",
            "angle": 180,
            "name": "button3"
        },
        {
            "id": "LOC_0038_0016",
            "gameObjectType": "TOGGLE_BUTTON",
            "angle": 180,
            "name": "button4"
        },
        {
            "id": "LOC_0005_0021",
            "gameObjectType": "LASERWALL_64",
            "name": "button2_TARGET",
            "disabled": "DISABLED_TYPE::RENDER_AND_PHYSICS"
        },
        {
            "id": "LOC_0034_0020",
            "gameObjectType": "LASERWALL_64",
            "name": "button1_TARGET",
            "disabled": "DISABLED_TYPE::RENDER_AND_PHYSICS"
        },
        {
            "id": "LOC_0004_0018",
            "gameObjectType": "LASERWALL_64",
            "name": "button3_TARGET",
            "disabled": "DISABLED_TYPE::RENDER_AND_PHYSICS"
        },
        {
            "id": "LOC_0027_0020",
            "gameObjectType": "LASERWALL_96",
            "name": "button1_TARGET",
            "disabled": "DISABLED_TYPE::RENDER_AND_PHYSICS"
        },
        {
            "id": "LOC_0064_0021",
            "gameObjectType": "LASERWALL_96",
            "angle": 90,
            "name": "EnemyCTrigger_TARGET"
        },
        {
            "id": "LOC_0036_0028",
            "gameObjectType": "LASERWALL_64",
            "angle": 90,
            "name": "button3_TARGET"
        },
        {
            "id": "LOC_0048_0006",
            "gameObjectType": "LASERWALL_128",
            "name": "button4_TARGET"
        },
        {
            "id": "LOC_0045_0015",
            "gameObjectType": "LASERWALL_64",
            "angle": 90,
            "name": "button4_TARGET"
        },
        {
            "id": "LOC_0055_0015",
            "gameObjectType": "LASERWALL_64",
            "angle": 90,
            "name": "button4_TARGET"
        },
        {
            "id": "LOC_0063_0014",
            "gameObjectType": "ESCAPE_STAIRS",
            "angle": 180
        },
        {
            "id": "LOC_0035_0016",
            "gameObjectType": "CHECKPOINT_3_A",
            "layer": "GameLayer::ABSTRACT"
        }

    ]
}